{
  "$type": "Octopus.Core.Model.Events.Event, Octopus.Core",
  "Id": "Events-75",
  "RelatedDocumentIds": [
    "Machines-21",
    "Environments-1"
  ],
  "ProjectId": null,
  "EnvironmentId": "Environments-1",
  "TenantId": null,
  "Category": "MachineHealthy",
  "UserId": "users-system",
  "Username": "system",
  "Occurred": "2018-01-14T14:08:01.4588864+00:00",
  "Message": "Machine WEB1 became healthy",
  "MessageReferences": [
    {
      "ReferencedDocumentId": "Machines-21",
      "StartIndex": 8,
      "Length": 4
    }
  ],
  "Comments": null,
  "Details": null,
  "IdentityEstablishedWith": "Unknown"
}